servicelayer/__init__.py
servicelayer/cache.py
servicelayer/env.py
servicelayer/extensions.py
servicelayer/jobs.py
servicelayer/logs.py
servicelayer/metrics.py
servicelayer/rate_limit.py
servicelayer/reporting.py
servicelayer/settings.py
servicelayer/tags.py
servicelayer/taskqueue.py
servicelayer/util.py
servicelayer/worker.py
servicelayer/archive/__init__.py
servicelayer/archive/archive.py
servicelayer/archive/file.py
servicelayer/archive/gs.py
servicelayer/archive/s3.py
servicelayer/archive/util.py
servicelayer/archive/virtual.py
servicelayer-1.25.2.dist-info/licenses/LICENSE
tests/__init__.py
tests/test_basic.py
tests/test_cache.py
tests/test_dataset.py
tests/test_extensions.py
tests/test_jobs.py
tests/test_rate_limit.py
tests/test_reporting.py
tests/test_tags.py
tests/test_taskqueue.py
tests/test_util.py
tests/test_worker.py
tests/archive/__init__.py
tests/archive/test_file.py
tests/archive/test_s3.py
servicelayer-1.25.2.dist-info/METADATA
servicelayer-1.25.2.dist-info/WHEEL
servicelayer-1.25.2.dist-info/entry_points.txt
servicelayer-1.25.2.dist-info/namespace_packages.txt
servicelayer-1.25.2.dist-info/top_level.txt
servicelayer-1.25.2.dist-info/zip-safe
servicelayer-1.25.2.dist-info/RECORD
