Metadata-Version: 2.4
Name: servicelayer
Version: 1.25.2
Summary: Basic remote service functions for alephdata components
Home-page: http://github.com/alephdata/servicelayer
Author: Organized Crime and Corruption Reporting Project
Author-email: data@occrp.org
License: MIT
Keywords: storage files s3
Classifier: Development Status :: 3 - Alpha
Classifier: Intended Audience :: Developers
Classifier: License :: OSI Approved :: MIT License
Classifier: Operating System :: OS Independent
Classifier: Programming Language :: Python :: 3.10
Classifier: Programming Language :: Python :: 3.11
Classifier: Programming Language :: Python :: 3.12
License-File: LICENSE
Requires-Dist: banal<2.0.0,>=1.0.6
Requires-Dist: normality<3.0.0,>=2.4.0
Requires-Dist: fakeredis<2.31.0,>=2.11.2
Requires-Dist: redis<=4.6.0
Requires-Dist: sqlalchemy<3.0.0,>=1.4.49
Requires-Dist: structlog<25.0.0,>=20.2.0
Requires-Dist: colorama<1.0.0,>=0.4.4
Requires-Dist: pika<2.0.0,>=1.3.1
Requires-Dist: prometheus-client<0.21.0,>=0.17.1
Provides-Extra: amazon
Requires-Dist: boto3<2.0.0,>=1.11.9; extra == "amazon"
Provides-Extra: google
Requires-Dist: grpcio<2.0.0,>=1.32.0; extra == "google"
Requires-Dist: google-cloud-storage<4.0.0,>=1.31.0; extra == "google"
Provides-Extra: dev
Requires-Dist: twine; extra == "dev"
Requires-Dist: moto<5; extra == "dev"
Requires-Dist: boto3<2.0.0,>=1.11.9; extra == "dev"
Requires-Dist: pytest>=3.6; extra == "dev"
Requires-Dist: coverage; extra == "dev"
Requires-Dist: pytest-cov; extra == "dev"
Requires-Dist: time-machine<3.0.0,>=2.14.1; extra == "dev"
Dynamic: author
Dynamic: author-email
Dynamic: classifier
Dynamic: description
Dynamic: description-content-type
Dynamic: home-page
Dynamic: keywords
Dynamic: license
Dynamic: license-file
Dynamic: provides-extra
Dynamic: requires-dist
Dynamic: summary
